motion/__init__.py
motion/cli.py
motion/marshal.py
motion/motion.py
motion/worker.py
motion-0.2.0.dist-info/METADATA
motion-0.2.0.dist-info/WHEEL
motion-0.2.0.dist-info/entry_points.txt
motion-0.2.0.dist-info/top_level.txt
motion-0.2.0.dist-info/RECORD
