Metadata-Version: 2.1
Name: motion
Version: 0.2.0
Summary: High-level library for dispatching and responding to tasks via AWS Kinesis
Home-page: UNKNOWN
Author: Evan Borgstrom
Author-email: eborgstrom@nerdwallet.com
License: Apache 2
Platform: UNKNOWN
Classifier: Development Status :: 4 - Beta
Classifier: Programming Language :: Python :: 3.6
Classifier: Programming Language :: Python :: 3.7
Classifier: Programming Language :: Python :: 3.8
Classifier: Intended Audience :: Developers
Classifier: License :: OSI Approved :: Apache Software License
Classifier: Natural Language :: English
Classifier: Programming Language :: Python
Classifier: Topic :: Internet
Classifier: Topic :: Software Development :: Libraries
